MANIFEST.in
README.rst
ez_setup.py
setup.py
giraf/__init__.py
giraf/__main__.py
giraf/api.py
giraf/const.py
giraf/enums.py
giraf/filter.py
giraf/helper.py
giraf/imgur.py
giraf/main.py
giraf/pager.py
giraf/version.py
giraf.egg-info/PKG-INFO
giraf.egg-info/SOURCES.txt
giraf.egg-info/dependency_links.txt
giraf.egg-info/entry_points.txt
giraf.egg-info/requires.txt
giraf.egg-info/top_level.txt
giraf/client/__init__.py
giraf/client/album_subcommands.py
giraf/client/all_subcommands.py
giraf/client/main_subcommands.py
giraf/client/printers.py
giraf/client/subcommand_mixin.py